django_requests_logger/__init__.py
django_requests_logger/admin.py
django_requests_logger/apps.py
django_requests_logger/callbacks.py
django_requests_logger/migrations/0001_initial.py
django_requests_logger/migrations/__init__.py
django_requests_logger/models.py
django_requests_logger/signals.py
django_requests_logger-1.0.0.dist-info/LICENSE
django_requests_logger-1.0.0.dist-info/METADATA
django_requests_logger-1.0.0.dist-info/WHEEL
django_requests_logger-1.0.0.dist-info/RECORD
