Metadata-Version: 2.1
Name: django-requests-logger
Version: 1.0.0
Summary: A django integration for requests.
License: MIT
Author: Miguel Ferrer
Author-email: ingferrermiguel@gmail.com
Requires-Python: >=3.7,<4.0
Classifier: License :: OSI Approved :: MIT License
Classifier: Programming Language :: Python :: 3
Classifier: Programming Language :: Python :: 3.7
Classifier: Programming Language :: Python :: 3.8
Classifier: Programming Language :: Python :: 3.9
Classifier: Programming Language :: Python :: 3.10
Classifier: Programming Language :: Python :: 3.11
Requires-Dist: django (>=3.2.0,<4.0.0)
Requires-Dist: requests (>=2.26.0,<3.0.0)
